{"uuid": "0441fe2b-22fd-11f1-8b52-44476701000f", "user_color": "black", "result": "loss", "time_class": "rapid", "opening_name": "Pirc Defense Modern Defense Geller System", "user_cpl": 67.9, "opp_cpl": 33.8, "user_blunders": 1, "user_mistakes": 4, "user_inaccuracies": 5, "opp_blunders": 0, "opp_mistakes": 2, "opp_inaccuracies": 5, "user_moves": 27, "move15_eval": -728, "max_adv": 82, "min_adv": -1127, "endgame_entry_eval": null, "endgame_entry_ply": null, "reached_endgame": false, "user_eval_curve": [-36, -35, -55, -37, -52, -44, -76, -30, -48, 23, 23, 38, 28, 36, 18, 82, -506, -480, -627, -543, -616, -601, -644, -606, -628, -559, -645, -557, -595, -633, -728, -698, -877, -901, -970, -789, -922, -890, -953, -804, -983, -1044, -1060, -1124, -1127, -1005, -1109, -1002, -1063, -1102, -994, -991, -991, -992, -997, -996]}